gancio_telegram_bot/__init__.py
gancio_telegram_bot/__main__.py
gancio_telegram_bot/callbacks/__init__.py
gancio_telegram_bot/callbacks/page_turn.py
gancio_telegram_bot/config.py
gancio_telegram_bot/handlers/__init__.py
gancio_telegram_bot/handlers/help.py
gancio_telegram_bot/handlers/show_calendar.py
gancio_telegram_bot/utils/__init__.py
gancio_telegram_bot/utils/utils.py
gancio_telegram_bot/viz/__init__.py
gancio_telegram_bot/viz/plots.py
gancio_telegram_bot-0.1.0.dist-info/LICENSE
gancio_telegram_bot-0.1.0.dist-info/WHEEL
gancio_telegram_bot-0.1.0.dist-info/METADATA
gancio_telegram_bot-0.1.0.dist-info/RECORD
