Metadata-Version: 2.1
Name: gancio-telegram-bot
Version: 0.1.0
Summary: A Telegram bot to interact with Gancio instances
Home-page: https://github.com/bendico765/gancio_telegram_bot
License: AGPL-3.0-only
Author: Gianluca Morcaldi
Author-email: bendico765@gmail.com
Requires-Python: >=3.10,<4.0
Classifier: License :: OSI Approved :: GNU Affero General Public License v3
Classifier: Programming Language :: Python :: 3
Classifier: Programming Language :: Python :: 3.10
Requires-Dist: aiohttp-client-cache (>=0.7.3,<0.8.0)
Requires-Dist: aiosqlite (>=0.17.0,<0.18.0)
Requires-Dist: gancio-requests (>=0.1.2,<0.2.0)
Requires-Dist: matplotlib (>=3.5.3,<4.0.0)
Requires-Dist: pandas (>=1.4.4,<2.0.0)
Requires-Dist: python-dotenv (>=0.21.0,<0.22.0)
Requires-Dist: python-telegram-bot (==20.0a4)
Requires-Dist: seaborn (>=0.12.0,<0.13.0)
Project-URL: Repository, https://github.com/bendico765/gancio_telegram_bot
